{
  "par_file": {
    "SIMULATION_TYPE": 1,
    "NOISE_TOMOGRAPHY": 0,
    "SAVE_FORWARD": false,
    "INVERSE_FWI_FULL_PROBLEM": false,
    "UTM_PROJECTION_ZONE": 11,
    "SUPPRESS_UTM_PROJECTION": true,
    "NPROC": 4,
    "NSTEP": 1000,
    "DT": 0.05,
    "LTS_MODE": false,
    "PARTITIONING_TYPE": 1,
    "USE_LDDRK": false,
    "INCREASE_CFL_FOR_LDDRK": false,
    "RATIO_BY_WHICH_TO_INCREASE_IT": 1.4,
    "NGNOD": 8,
    "MODEL": "default",
    "TOMOGRAPHY_PATH": "./DATA/tomo_files/",
    "SEP_MODEL_DIRECTORY": "./DATA/my_SEP_model/",
    "APPROXIMATE_OCEAN_LOAD": false,
    "TOPOGRAPHY": false,
    "ATTENUATION": false,
    "ANISOTROPY": false,
    "GRAVITY": false,
    "ATTENUATION_f0_REFERENCE": "0.33333d0",
    "MIN_ATTENUATION_PERIOD": "999999998.d0",
    "MAX_ATTENUATION_PERIOD": "999999999.d0",
    "COMPUTE_FREQ_BAND_AUTOMATIC": true,
    "USE_OLSEN_ATTENUATION": false,
    "OLSEN_ATTENUATION_RATIO": 0.05,
    "PML_CONDITIONS": false,
    "PML_INSTEAD_OF_FREE_SURFACE": false,
    "f0_FOR_PML": 0.05555,
    "STACEY_ABSORBING_CONDITIONS": false,
    "STACEY_INSTEAD_OF_FREE_SURFACE": false,
    "BOTTOM_FREE_SURFACE": false,
    "UNDO_ATTENUATION_AND_OR_PML": false,
    "NT_DUMP_ATTENUATION": 500,
    "CREATE_SHAKEMAP": false,
    "MOVIE_SURFACE": false,
    "MOVIE_TYPE": 1,
    "MOVIE_VOLUME": false,
    "SAVE_DISPLACEMENT": false,
    "MOVIE_VOLUME_STRESS": false,
    "USE_HIGHRES_FOR_MOVIES": false,
    "NTSTEP_BETWEEN_FRAMES": 100,
    "HDUR_MOVIE": 0.0,
    "SAVE_MESH_FILES": false,
    "LOCAL_PATH": "./OUTPUT_FILES/DATABASES_MPI",
    "NTSTEP_BETWEEN_OUTPUT_INFO": 100,
    "USE_SOURCES_RECEIVERS_Z": false,
    "USE_FORCE_POINT_SOURCE": false,
    "USE_RICKER_TIME_FUNCTION": true,
    "USE_EXTERNAL_SOURCE_FILE": false,
    "PRINT_SOURCE_TIME_FUNCTION": false,
    "USE_SOURCE_ENCODING": false,
    "NTSTEP_BETWEEN_OUTPUT_SEISMOS": 500,
    "NTSTEP_BETWEEN_OUTPUT_SAMPLE": 5,
    "SAVE_SEISMOGRAMS_DISPLACEMENT": true,
    "SAVE_SEISMOGRAMS_VELOCITY": true,
    "SAVE_SEISMOGRAMS_ACCELERATION": false,
    "SAVE_SEISMOGRAMS_PRESSURE": false,
    "SAVE_SEISMOGRAMS_STRAIN": false,
    "SAVE_SEISMOGRAMS_IN_ADJOINT_RUN": false,
    "USE_BINARY_FOR_SEISMOGRAMS": false,
    "SU_FORMAT": false,
    "ASDF_FORMAT": false,
    "HDF5_FORMAT": false,
    "WRITE_SEISMOGRAMS_BY_MAIN": true,
    "SAVE_ALL_SEISMOS_IN_ONE_FILE": false,
    "USE_TRICK_FOR_BETTER_PRESSURE": false,
    "OUTPUT_ENERGY": false,
    "NTSTEP_BETWEEN_OUTPUT_ENERGY": 10,
    "NTSTEP_BETWEEN_READ_ADJSRC": 0,
    "READ_ADJSRC_ASDF": false,
    "ANISOTROPIC_KL": false,
    "SAVE_TRANSVERSE_KL": false,
    "ANISOTROPIC_VELOCITY_KL": false,
    "APPROXIMATE_HESS_KL": false,
    "SAVE_MOHO_MESH": false,
    "COUPLE_WITH_INJECTION_TECHNIQUE": false,
    "INJECTION_TECHNIQUE_TYPE": 3,
    "MESH_A_CHUNK_OF_THE_EARTH": false,
    "TRACTION_PATH": "./DATA/AxiSEM_tractions/3/",
    "FKMODEL_FILE": "FKmodel",
    "RECIPROCITY_AND_KH_INTEGRAL": false,
    "NUMBER_OF_SIMULTANEOUS_RUNS": 1,
    "BROADCAST_SAME_MESH_AND_MODEL": false,
    "GPU_MODE": false,
    "ADIOS_ENABLED": false,
    "ADIOS_FOR_DATABASES": false,
    "ADIOS_FOR_MESH": false,
    "ADIOS_FOR_FORWARD_ARRAYS": false,
    "ADIOS_FOR_KERNELS": false,
    "ADIOS_FOR_UNDO_ATTENUATION": false,
    "HDF5_ENABLED": false,
    "HDF5_FOR_MOVIES": false,
    "HDF5_IO_NODES": 0
  },
  "mesh_par_file": {
    "LATITUDE_MIN": "0.d0",
    "LATITUDE_MAX": "4800.d0",
    "LONGITUDE_MIN": "0.d0",
    "LONGITUDE_MAX": "4800.d0",
    "DEPTH_BLOCK_KM": "4.8d0",
    "UTM_PROJECTION_ZONE": 0,
    "SUPPRESS_UTM_PROJECTION": true,
    "INTERFACES_FILE": "interfaces.dat",
    "CAVITY_FILE": "no_cavity.dat",
    "NEX_XI": 8,
    "NEX_ETA": 8,
    "NPROC_XI": 2,
    "NPROC_ETA": 2,
    "USE_REGULAR_MESH": true,
    "NDOUBLINGS": 0,
    "NZ_DOUBLING_1": 0,
    "NZ_DOUBLING_2": 0,
    "CREATE_ABAQUS_FILES": false,
    "CREATE_DX_FILES": false,
    "CREATE_VTK_FILES": false,
    "SAVE_MESH_AS_CUBIT": false,
    "LOCAL_PATH": "./DATABASES_MPI",
    "THICKNESS_OF_X_PML": "600.0d0",
    "THICKNESS_OF_Y_PML": "600.0d0",
    "THICKNESS_OF_Z_PML": "600.0d0",
    "NMATERIALS": 4,
    "NREGIONS": 4
  },
  "source": {
    "event_name": "PDE  1999 01 01 00 00 00.00  67000 67000 -25000 4.2 4.2 homog_test",
    "event name": "homog_test",
    "time shift": 0.0,
    "half duration": 5.0,
    "latorUTM": 67000.0,
    "longorUTM": 67000.0,
    "depth": 30.0,
    "Mrr": -7.6e+27,
    "Mtt": 7.7e+27,
    "Mpp": -2e+26,
    "Mrt": -2.5e+28,
    "Mrp": 4e+26,
    "Mtp": -2.5e+27
  },
  "stations": [
    {
      "name": "ST001",
      "network": "GE",
      "lat": 500.0,
      "lon": 500.0,
      "elevation": 0.0,
      "burial": 0.0
    },
    {
      "name": "ST002",
      "network": "GE",
      "lat": 500.0,
      "lon": 1000.0,
      "elevation": 0.0,
      "burial": 0.0
    },
    {
      "name": "ST003",
      "network": "GE",
      "lat": 500.0,
      "lon": 1500.0,
      "elevation": 0.0,
      "burial": 0.0
    },
    {
      "name": "ST004",
      "network": "GE",
      "lat": 1500.0,
      "lon": 500.0,
      "elevation": 0.0,
      "burial": 0.0
    },
    {
      "name": "ST005",
      "network": "GE",
      "lat": 1500.0,
      "lon": 1000.0,
      "elevation": 0.0,
      "burial": 0.0
    },
    {
      "name": "ST006",
      "network": "GE",
      "lat": 1500.0,
      "lon": 1500.0,
      "elevation": 0.0,
      "burial": 0.0
    }
  ]
}